LICENSE
MANIFEST.in
README.rst
setup.py
django_crud_reactjs_fagsoft.egg-info/PKG-INFO
django_crud_reactjs_fagsoft.egg-info/SOURCES.txt
django_crud_reactjs_fagsoft.egg-info/dependency_links.txt
django_crud_reactjs_fagsoft.egg-info/requires.txt
django_crud_reactjs_fagsoft.egg-info/top_level.txt
fagsoft/__init__.py
fagsoft/app_configurations/__init__.py
fagsoft/app_configurations/admin.py
fagsoft/app_configurations/apps.py
fagsoft/app_configurations/models.py
fagsoft/app_configurations/serializers.py
fagsoft/app_configurations/services.py
fagsoft/app_configurations/signals.py
fagsoft/app_configurations/tests.py
fagsoft/app_configurations/urls.py
fagsoft/app_configurations/views.py
fagsoft/app_configurations/migrations/0001_initial.py
fagsoft/app_configurations/migrations/0002_auto_20200411_0132.py
fagsoft/app_configurations/migrations/0003_auto_20200528_0402.py
fagsoft/app_configurations/migrations/__init__.py
fagsoft/countries/__init__.py
fagsoft/countries/admin.py
fagsoft/countries/apps.py
fagsoft/countries/models.py
fagsoft/countries/serializers.py
fagsoft/countries/services.py
fagsoft/countries/tests.py
fagsoft/countries/urls.py
fagsoft/countries/views.py
fagsoft/countries/migrations/0001_initial.py
fagsoft/countries/migrations/0002_auto_20200503_0312.py
fagsoft/countries/migrations/0003_auto_20200503_0312.py
fagsoft/countries/migrations/0004_auto_20200503_0323.py
fagsoft/countries/migrations/0005_auto_20200503_0432.py
fagsoft/countries/migrations/0006_auto_20200504_1407.py
fagsoft/countries/migrations/__init__.py
fagsoft/permissions/__init__.py
fagsoft/permissions/admin.py
fagsoft/permissions/apps.py
fagsoft/permissions/models.py
fagsoft/permissions/serializers.py
fagsoft/permissions/tests.py
fagsoft/permissions/urls.py
fagsoft/permissions/views.py
fagsoft/permissions/migrations/0001_initial.py
fagsoft/permissions/migrations/0002_auto_20200404_1600.py
fagsoft/permissions/migrations/__init__.py
fagsoft/users_extended/__init__.py
fagsoft/users_extended/admin.py
fagsoft/users_extended/apps.py
fagsoft/users_extended/models.py
fagsoft/users_extended/serializers.py
fagsoft/users_extended/services.py
fagsoft/users_extended/signals.py
fagsoft/users_extended/tests.py
fagsoft/users_extended/urls.py
